<?xml version="1.0" encoding="UTF-8"?>
<!--
	ABD DOMESTICATED ANIMAL ATTRIBUTES
	DomesticatedAnimalAttributes.xml
-->
<METADATA
	xmlns:xsi="http://www.w3.org/2001/XMLSchema-instance"
	xsi:noNamespaceSchemaLocation="https://gist.githubusercontent.com/milko/f2dcea3c3a94f69bb0bb/raw/715d8fd15a66ad25466c9efc4f767fd31fc9a21a/Dictionary.xsd">
	
	<!-- Domesticated animal species attributes -->
	
	<!-- abdh:Q5.1 -->
	<META>
		<TERM ns="abdh" lid="Q5.1">
			<item const="kTAG_LABEL">
				<item>
					<item const="kTAG_LANGUAGE">en</item>
					<item const="kTAG_TEXT"><![CDATA[How many animals of this species do you own]]></item>
				</item>
			</item>
		</TERM>
		<TAG>
			<item const="kTAG_TERMS">
				<item>abdh:Q5.1</item>
			</item>
			<item const="kTAG_DATA_TYPE">:type:int</item>
			<item const="kTAG_DATA_KIND">
				<item>:type:quantitative</item>
			</item>
			<item const="kTAG_SYNONYM">
				<item>Q5.1</item>
			</item>
		</TAG>
		<NODE tag="abdh:Q5.1">
			<item const="kTAG_NODE_TYPE">
				<item>:kind:property-node</item>
			</item>
		</NODE>
		<EDGE>
			<item const="kTAG_PREDICATE">:predicate:PROPERTY-OF</item>
			<item const="kTAG_OBJECT" node="tag">abdh:species</item>
		</EDGE>
	</META>
	
	<!-- abdh:Q5.2a -->
	<META>
		<TERM ns="abdh" lid="Q5.2a">
			<item const="kTAG_LABEL">
				<item>
					<item const="kTAG_LANGUAGE">en</item>
					<item const="kTAG_TEXT"><![CDATA[What products did you derive from this species]]></item>
				</item>
			</item>
		</TERM>
		<TAG>
			<item const="kTAG_TERMS">
				<item>abdh:Q5.2a</item>
			</item>
			<item const="kTAG_DATA_TYPE">:type:enum-set</item>
			<item const="kTAG_DATA_KIND">
				<item>:type:categorical</item>
				<item>:type:full-text-03</item>
				<item>:type:summary</item>
			</item>
			<item const="kTAG_SYNONYM">
				<item>Q5.2a</item>
			</item>
		</TAG>
		<NODE tag="abdh:Q5.2a">
			<item const="kTAG_NODE_TYPE">
				<item>:kind:property-node</item>
			</item>
		</NODE>
		<NODE term="abdh:Q5.2a">
			<item const="kTAG_NODE_TYPE">
				<item>:type:node:type</item>
				<item>:kind:enumerated-node</item>
			</item>
		</NODE>
		<EDGE>
			<item const="kTAG_SUBJECT" node="term">abdh:Q5.2a</item>
			<item const="kTAG_PREDICATE">:predicate:TYPE-OF</item>
			<item const="kTAG_OBJECT" node="tag">abdh:Q5.2a</item>
		</EDGE>
		<EDGE>
			<item const="kTAG_SUBJECT" node="tag">abdh:Q5.2a</item>
			<item const="kTAG_PREDICATE">:predicate:PROPERTY-OF</item>
			<item const="kTAG_OBJECT" node="tag">abdh:species</item>
		</EDGE>
	</META>
	<!-- abdh:Q5.2a:1 -->
	<META>
		<TERM ns="abdh:Q5.2a" lid="1">
			<item const="kTAG_LABEL">
				<item>
					<item const="kTAG_LANGUAGE">en</item>
					<item const="kTAG_TEXT"><![CDATA[Milk]]></item>
				</item>
			</item>
		</TERM>
		<NODE>
			<item const="kTAG_NODE_TYPE">
				<item>:type:node:enumeration</item>
			</item>
		</NODE>
		<EDGE>
			<item const="kTAG_PREDICATE">:predicate:ENUM-OF</item>
			<item const="kTAG_OBJECT" node="term">abdh:Q5.2a</item>
		</EDGE>
	</META>
	<!-- abdh:Q5.2a:2 -->
	<META>
		<TERM ns="abdh:Q5.2a" lid="2">
			<item const="kTAG_LABEL">
				<item>
					<item const="kTAG_LANGUAGE">en</item>
					<item const="kTAG_TEXT"><![CDATA[Dung for fuel]]></item>
				</item>
			</item>
		</TERM>
		<NODE>
			<item const="kTAG_NODE_TYPE">
				<item>:type:node:enumeration</item>
			</item>
		</NODE>
		<EDGE>
			<item const="kTAG_PREDICATE">:predicate:ENUM-OF</item>
			<item const="kTAG_OBJECT" node="term">abdh:Q5.2a</item>
		</EDGE>
	</META>
	<!-- abdh:Q5.2a:3 -->
	<META>
		<TERM ns="abdh:Q5.2a" lid="3">
			<item const="kTAG_LABEL">
				<item>
					<item const="kTAG_LANGUAGE">en</item>
					<item const="kTAG_TEXT"><![CDATA[Dung as fertilizer]]></item>
				</item>
			</item>
		</TERM>
		<NODE>
			<item const="kTAG_NODE_TYPE">
				<item>:type:node:enumeration</item>
			</item>
		</NODE>
		<EDGE>
			<item const="kTAG_PREDICATE">:predicate:ENUM-OF</item>
			<item const="kTAG_OBJECT" node="term">abdh:Q5.2a</item>
		</EDGE>
	</META>
	<!-- abdh:Q5.2a:4 -->
	<META>
		<TERM ns="abdh:Q5.2a" lid="4">
			<item const="kTAG_LABEL">
				<item>
					<item const="kTAG_LANGUAGE">en</item>
					<item const="kTAG_TEXT"><![CDATA[Hides]]></item>
				</item>
			</item>
		</TERM>
		<NODE>
			<item const="kTAG_NODE_TYPE">
				<item>:type:node:enumeration</item>
			</item>
		</NODE>
		<EDGE>
			<item const="kTAG_PREDICATE">:predicate:ENUM-OF</item>
			<item const="kTAG_OBJECT" node="term">abdh:Q5.2a</item>
		</EDGE>
	</META>
	<!-- abdh:Q5.2a:5 -->
	<META>
		<TERM ns="abdh:Q5.2a" lid="5">
			<item const="kTAG_LABEL">
				<item>
					<item const="kTAG_LANGUAGE">en</item>
					<item const="kTAG_TEXT"><![CDATA[Other]]></item>
				</item>
			</item>
		</TERM>
		<NODE>
			<item const="kTAG_NODE_TYPE">
				<item>:type:node:enumeration</item>
			</item>
		</NODE>
		<EDGE>
			<item const="kTAG_PREDICATE">:predicate:ENUM-OF</item>
			<item const="kTAG_OBJECT" node="term">abdh:Q5.2a</item>
		</EDGE>
	</META>
	
	<!-- abdh:Q5.2b -->
	<META>
		<TERM ns="abdh" lid="Q5.2b">
			<item const="kTAG_LABEL">
				<item>
					<item const="kTAG_LANGUAGE">en</item>
					<item const="kTAG_TEXT"><![CDATA[What products did you derive from this species (other specification)]]></item>
				</item>
			</item>
		</TERM>
		<TAG>
			<item const="kTAG_TERMS">
				<item>abdh:Q5.2b</item>
			</item>
			<item const="kTAG_DATA_TYPE">:type:string</item>
			<item const="kTAG_DATA_KIND">
				<item>:type:discrete</item>
				<item>:type:list</item>
				<item>:type:full-text-03</item>
			</item>
			<item const="kTAG_SYNONYM">
				<item>Q5.2b</item>
			</item>
		</TAG>
		<NODE tag="abdh:Q5.2b">
			<item const="kTAG_NODE_TYPE">
				<item>:kind:property-node</item>
			</item>
		</NODE>
		<EDGE>
			<item const="kTAG_PREDICATE">:predicate:PROPERTY-OF</item>
			<item const="kTAG_OBJECT" node="tag">abdh:species</item>
		</EDGE>
	</META>
	
	<!-- abdh:Q5.3a -->
	<META>
		<TERM ns="abdh" lid="Q5.3a">
			<item const="kTAG_LABEL">
				<item>
					<item const="kTAG_LANGUAGE">en</item>
					<item const="kTAG_TEXT"><![CDATA[Objectives for products derived from this species]]></item>
				</item>
			</item>
		</TERM>
		<TAG>
			<item const="kTAG_TERMS">
				<item>abdh:Q5.3a</item>
			</item>
			<item const="kTAG_DATA_TYPE">:type:enum-set</item>
			<item const="kTAG_DATA_KIND">
				<item>:type:categorical</item>
				<item>:type:full-text-03</item>
				<item>:type:summary</item>
			</item>
			<item const="kTAG_SYNONYM">
				<item>Q5.3a</item>
			</item>
		</TAG>
		<NODE tag="abdh:Q5.3a">
			<item const="kTAG_NODE_TYPE">
				<item>:kind:property-node</item>
			</item>
		</NODE>
		<NODE term="abdh:Q5.3a">
			<item const="kTAG_NODE_TYPE">
				<item>:type:node:type</item>
				<item>:kind:enumerated-node</item>
			</item>
		</NODE>
		<EDGE>
			<item const="kTAG_SUBJECT" node="term">abdh:Q5.3a</item>
			<item const="kTAG_PREDICATE">:predicate:TYPE-OF</item>
			<item const="kTAG_OBJECT" node="tag">abdh:Q5.3a</item>
		</EDGE>
		<EDGE>
			<item const="kTAG_SUBJECT" node="tag">abdh:Q5.3a</item>
			<item const="kTAG_PREDICATE">:predicate:PROPERTY-OF</item>
			<item const="kTAG_OBJECT" node="tag">abdh:species</item>
		</EDGE>
	</META>
	<!-- abdh:Q5.3a:1 -->
	<META>
		<TERM ns="abdh:Q5.3a" lid="1">
			<item const="kTAG_LABEL">
				<item>
					<item const="kTAG_LANGUAGE">en</item>
					<item const="kTAG_TEXT"><![CDATA[Direct use by household]]></item>
				</item>
			</item>
		</TERM>
		<NODE>
			<item const="kTAG_NODE_TYPE">
				<item>:type:node:enumeration</item>
			</item>
		</NODE>
		<EDGE>
			<item const="kTAG_PREDICATE">:predicate:ENUM-OF</item>
			<item const="kTAG_OBJECT" node="term">abdh:Q5.3a</item>
		</EDGE>
	</META>
	<!-- abdh:Q5.3a:2 -->
	<META>
		<TERM ns="abdh:Q5.3a" lid="2">
			<item const="kTAG_LABEL">
				<item>
					<item const="kTAG_LANGUAGE">en</item>
					<item const="kTAG_TEXT"><![CDATA[For sale]]></item>
				</item>
			</item>
		</TERM>
		<NODE>
			<item const="kTAG_NODE_TYPE">
				<item>:type:node:enumeration</item>
			</item>
		</NODE>
		<EDGE>
			<item const="kTAG_PREDICATE">:predicate:ENUM-OF</item>
			<item const="kTAG_OBJECT" node="term">abdh:Q5.3a</item>
		</EDGE>
	</META>
	<!-- abdh:Q5.3a:3 -->
	<META>
		<TERM ns="abdh:Q5.3a" lid="3">
			<item const="kTAG_LABEL">
				<item>
					<item const="kTAG_LANGUAGE">en</item>
					<item const="kTAG_TEXT"><![CDATA[Both]]></item>
				</item>
			</item>
		</TERM>
		<NODE>
			<item const="kTAG_NODE_TYPE">
				<item>:type:node:enumeration</item>
			</item>
		</NODE>
		<EDGE>
			<item const="kTAG_PREDICATE">:predicate:ENUM-OF</item>
			<item const="kTAG_OBJECT" node="term">abdh:Q5.3a</item>
		</EDGE>
	</META>
	<!-- abdh:Q5.3a:4 -->
	<META>
		<TERM ns="abdh:Q5.3a" lid="4">
			<item const="kTAG_LABEL">
				<item>
					<item const="kTAG_LANGUAGE">en</item>
					<item const="kTAG_TEXT"><![CDATA[Other]]></item>
				</item>
			</item>
		</TERM>
		<NODE>
			<item const="kTAG_NODE_TYPE">
				<item>:type:node:enumeration</item>
			</item>
		</NODE>
		<EDGE>
			<item const="kTAG_PREDICATE">:predicate:ENUM-OF</item>
			<item const="kTAG_OBJECT" node="term">abdh:Q5.3a</item>
		</EDGE>
	</META>
	
	<!-- abdh:Q5.3b -->
	<META>
		<TERM ns="abdh" lid="Q5.3b">
			<item const="kTAG_LABEL">
				<item>
					<item const="kTAG_LANGUAGE">en</item>
					<item const="kTAG_TEXT"><![CDATA[Objectives for products derived from this species (other specification)]]></item>
				</item>
			</item>
		</TERM>
		<TAG>
			<item const="kTAG_TERMS">
				<item>abdh:Q5.3b</item>
			</item>
			<item const="kTAG_DATA_TYPE">:type:string</item>
			<item const="kTAG_DATA_KIND">
				<item>:type:discrete</item>
				<item>:type:list</item>
				<item>:type:full-text-03</item>
			</item>
			<item const="kTAG_SYNONYM">
				<item>Q5.3b</item>
			</item>
		</TAG>
		<NODE tag="abdh:Q5.3b">
			<item const="kTAG_NODE_TYPE">
				<item>:kind:property-node</item>
			</item>
		</NODE>
		<EDGE>
			<item const="kTAG_PREDICATE">:predicate:PROPERTY-OF</item>
			<item const="kTAG_OBJECT" node="tag">abdh:species</item>
		</EDGE>
	</META>
	
	<!-- abdh:Q5.4 -->
	<META>
		<TERM ns="abdh" lid="Q5.4">
			<item const="kTAG_LABEL">
				<item>
					<item const="kTAG_LANGUAGE">en</item>
					<item const="kTAG_TEXT"><![CDATA[How many breeds of this species did you maintain]]></item>
				</item>
			</item>
		</TERM>
		<TAG>
			<item const="kTAG_TERMS">
				<item>abdh:Q5.4</item>
			</item>
			<item const="kTAG_DATA_TYPE">:type:int</item>
			<item const="kTAG_DATA_KIND">
				<item>:type:quantitative</item>
			</item>
			<item const="kTAG_SYNONYM">
				<item>Q5.4</item>
			</item>
		</TAG>
		<NODE tag="abdh:Q5.4">
			<item const="kTAG_NODE_TYPE">
				<item>:kind:property-node</item>
			</item>
		</NODE>
		<EDGE>
			<item const="kTAG_PREDICATE">:predicate:PROPERTY-OF</item>
			<item const="kTAG_OBJECT" node="tag">abdh:species</item>
		</EDGE>
	</META>
	
	<!-- abdh:Q5.5 -->
	<META>
		<TERM ns="abdh" lid="Q5.5">
			<item const="kTAG_LABEL">
				<item>
					<item const="kTAG_LANGUAGE">en</item>
					<item const="kTAG_TEXT"><![CDATA[How many of these breeds are local]]></item>
				</item>
			</item>
		</TERM>
		<TAG>
			<item const="kTAG_TERMS">
				<item>abdh:Q5.5</item>
			</item>
			<item const="kTAG_DATA_TYPE">:type:int</item>
			<item const="kTAG_DATA_KIND">
				<item>:type:quantitative</item>
			</item>
			<item const="kTAG_SYNONYM">
				<item>Q5.5</item>
			</item>
		</TAG>
		<NODE tag="abdh:Q5.5">
			<item const="kTAG_NODE_TYPE">
				<item>:kind:property-node</item>
			</item>
		</NODE>
		<EDGE>
			<item const="kTAG_PREDICATE">:predicate:PROPERTY-OF</item>
			<item const="kTAG_OBJECT" node="tag">abdh:species</item>
		</EDGE>
	</META>
	
	<!-- abdh:Q5.6 -->
	<META>
		<TERM ns="abdh" lid="Q5.6">
			<item const="kTAG_LABEL">
				<item>
					<item const="kTAG_LANGUAGE">en</item>
					<item const="kTAG_TEXT"><![CDATA[How many of these breeds are improved]]></item>
				</item>
			</item>
		</TERM>
		<TAG>
			<item const="kTAG_TERMS">
				<item>abdh:Q5.6</item>
			</item>
			<item const="kTAG_DATA_TYPE">:type:int</item>
			<item const="kTAG_DATA_KIND">
				<item>:type:quantitative</item>
			</item>
			<item const="kTAG_SYNONYM">
				<item>Q5.6</item>
			</item>
		</TAG>
		<NODE tag="abdh:Q5.6">
			<item const="kTAG_NODE_TYPE">
				<item>:kind:property-node</item>
			</item>
		</NODE>
		<EDGE>
			<item const="kTAG_PREDICATE">:predicate:PROPERTY-OF</item>
			<item const="kTAG_OBJECT" node="tag">abdh:species</item>
		</EDGE>
	</META>
	
	<!-- abdh:Q5.7 -->
	<META>
		<TERM ns="abdh" lid="Q5.7">
			<item const="kTAG_LABEL">
				<item>
					<item const="kTAG_LANGUAGE">en</item>
					<item const="kTAG_TEXT"><![CDATA[How many of these breeds are a mixture of local and improved]]></item>
				</item>
			</item>
		</TERM>
		<TAG>
			<item const="kTAG_TERMS">
				<item>abdh:Q5.7</item>
			</item>
			<item const="kTAG_DATA_TYPE">:type:int</item>
			<item const="kTAG_DATA_KIND">
				<item>:type:quantitative</item>
			</item>
			<item const="kTAG_SYNONYM">
				<item>Q5.7</item>
			</item>
		</TAG>
		<NODE tag="abdh:Q5.7">
			<item const="kTAG_NODE_TYPE">
				<item>:kind:property-node</item>
			</item>
		</NODE>
		<EDGE>
			<item const="kTAG_PREDICATE">:predicate:PROPERTY-OF</item>
			<item const="kTAG_OBJECT" node="tag">abdh:species</item>
		</EDGE>
	</META>
	
	<!-- abdh:Q5.8 -->
	<META>
		<TERM ns="abdh" lid="Q5.8">
			<item const="kTAG_LABEL">
				<item>
					<item const="kTAG_LANGUAGE">en</item>
					<item const="kTAG_TEXT"><![CDATA[How many of these breeds are a mixture of different local breeds]]></item>
				</item>
			</item>
		</TERM>
		<TAG>
			<item const="kTAG_TERMS">
				<item>abdh:Q5.8</item>
			</item>
			<item const="kTAG_DATA_TYPE">:type:int</item>
			<item const="kTAG_DATA_KIND">
				<item>:type:quantitative</item>
			</item>
			<item const="kTAG_SYNONYM">
				<item>Q5.8</item>
			</item>
		</TAG>
		<NODE tag="abdh:Q5.8">
			<item const="kTAG_NODE_TYPE">
				<item>:kind:property-node</item>
			</item>
		</NODE>
		<EDGE>
			<item const="kTAG_PREDICATE">:predicate:PROPERTY-OF</item>
			<item const="kTAG_OBJECT" node="tag">abdh:species</item>
		</EDGE>
	</META>
	
	<!-- abdh:Q5.9 -->
	<META>
		<TERM ns="abdh" lid="Q5.9">
			<item const="kTAG_LABEL">
				<item>
					<item const="kTAG_LANGUAGE">en</item>
					<item const="kTAG_TEXT"><![CDATA[How many did you purchase]]></item>
				</item>
			</item>
		</TERM>
		<TAG>
			<item const="kTAG_TERMS">
				<item>abdh:Q5.9</item>
			</item>
			<item const="kTAG_DATA_TYPE">:type:int</item>
			<item const="kTAG_DATA_KIND">
				<item>:type:quantitative</item>
			</item>
			<item const="kTAG_SYNONYM">
				<item>Q5.9</item>
			</item>
		</TAG>
		<NODE tag="abdh:Q5.9">
			<item const="kTAG_NODE_TYPE">
				<item>:kind:property-node</item>
			</item>
		</NODE>
		<EDGE>
			<item const="kTAG_PREDICATE">:predicate:PROPERTY-OF</item>
			<item const="kTAG_OBJECT" node="tag">abdh:species</item>
		</EDGE>
	</META>
	
	<!-- abdh:Q5.10 -->
	<META>
		<TERM ns="abdh" lid="Q5.10">
			<item const="kTAG_LABEL">
				<item>
					<item const="kTAG_LANGUAGE">en</item>
					<item const="kTAG_TEXT"><![CDATA[How many did you sell]]></item>
				</item>
			</item>
		</TERM>
		<TAG>
			<item const="kTAG_TERMS">
				<item>abdh:Q5.10</item>
			</item>
			<item const="kTAG_DATA_TYPE">:type:int</item>
			<item const="kTAG_DATA_KIND">
				<item>:type:quantitative</item>
			</item>
			<item const="kTAG_SYNONYM">
				<item>Q5.10</item>
			</item>
		</TAG>
		<NODE tag="abdh:Q5.10">
			<item const="kTAG_NODE_TYPE">
				<item>:kind:property-node</item>
			</item>
		</NODE>
		<EDGE>
			<item const="kTAG_PREDICATE">:predicate:PROPERTY-OF</item>
			<item const="kTAG_OBJECT" node="tag">abdh:species</item>
		</EDGE>
	</META>
	
	<!-- abdh:Q5.11 -->
	<META>
		<TERM ns="abdh" lid="Q5.11">
			<item const="kTAG_LABEL">
				<item>
					<item const="kTAG_LANGUAGE">en</item>
					<item const="kTAG_TEXT"><![CDATA[To whom did you sell]]></item>
				</item>
			</item>
		</TERM>
		<TAG>
			<item const="kTAG_TERMS">
				<item>abdh:Q5.11</item>
			</item>
			<item const="kTAG_DATA_TYPE">:type:string</item>
			<item const="kTAG_DATA_KIND">
				<item>:type:categorical</item>
				<item>:type:list</item>
				<item>:type:full-text-03</item>
			</item>
			<item const="kTAG_SYNONYM">
				<item>Q5.11</item>
			</item>
		</TAG>
		<NODE tag="abdh:Q5.11">
			<item const="kTAG_NODE_TYPE">
				<item>:kind:property-node</item>
			</item>
		</NODE>
		<EDGE>
			<item const="kTAG_PREDICATE">:predicate:PROPERTY-OF</item>
			<item const="kTAG_OBJECT" node="tag">abdh:species</item>
		</EDGE>
	</META>
	
	<!-- abdh:Q5.12 -->
	<META>
		<TERM ns="abdh" lid="Q5.12">
			<item const="kTAG_LABEL">
				<item>
					<item const="kTAG_LANGUAGE">en</item>
					<item const="kTAG_TEXT"><![CDATA[Where did you sell]]></item>
				</item>
			</item>
		</TERM>
		<TAG>
			<item const="kTAG_TERMS">
				<item>abdh:Q5.12</item>
			</item>
			<item const="kTAG_DATA_TYPE">:type:string</item>
			<item const="kTAG_DATA_KIND">
				<item>:type:categorical</item>
				<item>:type:list</item>
				<item>:type:full-text-03</item>
			</item>
			<item const="kTAG_SYNONYM">
				<item>Q5.12</item>
			</item>
		</TAG>
		<NODE tag="abdh:Q5.12">
			<item const="kTAG_NODE_TYPE">
				<item>:kind:property-node</item>
			</item>
		</NODE>
		<EDGE>
			<item const="kTAG_PREDICATE">:predicate:PROPERTY-OF</item>
			<item const="kTAG_OBJECT" node="tag">abdh:species</item>
		</EDGE>
	</META>
	
	<!-- abdh:Q5.13 -->
	<META>
		<TERM ns="abdh" lid="Q5.13">
			<item const="kTAG_LABEL">
				<item>
					<item const="kTAG_LANGUAGE">en</item>
					<item const="kTAG_TEXT"><![CDATA[Did you participate in animal fairs for buying/selling]]></item>
				</item>
			</item>
		</TERM>
		<TAG>
			<item const="kTAG_TERMS">
				<item>abdh:Q5.13</item>
			</item>
			<item const="kTAG_DATA_TYPE">:type:enum</item>
			<item const="kTAG_DATA_KIND">
				<item>:type:categorical</item>
				<item>:type:summary</item>
			</item>
			<item const="kTAG_SYNONYM">
				<item>Q5.13</item>
			</item>
		</TAG>
		<NODE tag="abdh:Q5.13">
			<item const="kTAG_NODE_TYPE">
				<item>:kind:property-node</item>
			</item>
		</NODE>
		<NODE term="abdh:Q5.13">
			<item const="kTAG_NODE_TYPE">
				<item>:type:node:type</item>
				<item>:kind:enumerated-node</item>
			</item>
		</NODE>
		<EDGE>
			<item const="kTAG_SUBJECT" node="term">abdh:Q5.13</item>
			<item const="kTAG_PREDICATE">:predicate:TYPE-OF</item>
			<item const="kTAG_OBJECT" node="tag">abdh:Q5.13</item>
		</EDGE>
		<EDGE>
			<item const="kTAG_SUBJECT" node="tag">abdh:Q5.13</item>
			<item const="kTAG_PREDICATE">:predicate:PROPERTY-OF</item>
			<item const="kTAG_OBJECT" node="tag">abdh:species</item>
		</EDGE>
	</META>
	<!-- abdh:Q5.13:0 -->
	<META>
		<TERM ns="abdh:Q5.13" lid="0">
			<item const="kTAG_LABEL">
				<item>
					<item const="kTAG_LANGUAGE">en</item>
					<item const="kTAG_TEXT"><![CDATA[No]]></item>
				</item>
			</item>
		</TERM>
		<NODE>
			<item const="kTAG_NODE_TYPE">
				<item>:type:node:enumeration</item>
			</item>
		</NODE>
		<EDGE>
			<item const="kTAG_PREDICATE">:predicate:ENUM-OF</item>
			<item const="kTAG_OBJECT" node="term">abdh:Q5.13</item>
		</EDGE>
	</META>
	<!-- abdh:Q5.13:1 -->
	<META>
		<TERM ns="abdh:Q5.13" lid="1">
			<item const="kTAG_LABEL">
				<item>
					<item const="kTAG_LANGUAGE">en</item>
					<item const="kTAG_TEXT"><![CDATA[Yes]]></item>
				</item>
			</item>
		</TERM>
		<NODE>
			<item const="kTAG_NODE_TYPE">
				<item>:type:node:enumeration</item>
			</item>
		</NODE>
		<EDGE>
			<item const="kTAG_PREDICATE">:predicate:ENUM-OF</item>
			<item const="kTAG_OBJECT" node="term">abdh:Q5.13</item>
		</EDGE>
	</META>
	
	<!-- abdh:Q5.14a -->
	<META>
		<TERM ns="abdh" lid="Q5.14a">
			<item const="kTAG_LABEL">
				<item>
					<item const="kTAG_LANGUAGE">en</item>
					<item const="kTAG_TEXT"><![CDATA[Who takes care of the species]]></item>
				</item>
			</item>
		</TERM>
		<TAG>
			<item const="kTAG_TERMS">
				<item>abdh:Q5.14a</item>
			</item>
			<item const="kTAG_DATA_TYPE">:type:enum-set</item>
			<item const="kTAG_DATA_KIND">
				<item>:type:categorical</item>
				<item>:type:full-text-03</item>
				<item>:type:summary</item>
			</item>
			<item const="kTAG_SYNONYM">
				<item>Q5.14a</item>
			</item>
		</TAG>
		<NODE tag="abdh:Q5.14a">
			<item const="kTAG_NODE_TYPE">
				<item>:kind:property-node</item>
			</item>
		</NODE>
		<NODE term="abdh:Q5.14a">
			<item const="kTAG_NODE_TYPE">
				<item>:type:node:type</item>
				<item>:kind:enumerated-node</item>
			</item>
		</NODE>
		<EDGE>
			<item const="kTAG_SUBJECT" node="term">abdh:Q5.14a</item>
			<item const="kTAG_PREDICATE">:predicate:TYPE-OF</item>
			<item const="kTAG_OBJECT" node="tag">abdh:Q5.14a</item>
		</EDGE>
		<EDGE>
			<item const="kTAG_SUBJECT" node="tag">abdh:Q5.14a</item>
			<item const="kTAG_PREDICATE">:predicate:PROPERTY-OF</item>
			<item const="kTAG_OBJECT" node="tag">abdh:species</item>
		</EDGE>
	</META>
	<!-- abdh:Q5.14a:1 -->
	<META>
		<TERM ns="abdh:Q5.14a" lid="1">
			<item const="kTAG_LABEL">
				<item>
					<item const="kTAG_LANGUAGE">en</item>
					<item const="kTAG_TEXT"><![CDATA[Husband]]></item>
				</item>
			</item>
		</TERM>
		<NODE>
			<item const="kTAG_NODE_TYPE">
				<item>:type:node:enumeration</item>
			</item>
		</NODE>
		<EDGE>
			<item const="kTAG_PREDICATE">:predicate:ENUM-OF</item>
			<item const="kTAG_OBJECT" node="term">abdh:Q5.14a</item>
		</EDGE>
	</META>
	<!-- abdh:Q5.14a:2 -->
	<META>
		<TERM ns="abdh:Q5.14a" lid="2">
			<item const="kTAG_LABEL">
				<item>
					<item const="kTAG_LANGUAGE">en</item>
					<item const="kTAG_TEXT"><![CDATA[Wife]]></item>
				</item>
			</item>
		</TERM>
		<NODE>
			<item const="kTAG_NODE_TYPE">
				<item>:type:node:enumeration</item>
			</item>
		</NODE>
		<EDGE>
			<item const="kTAG_PREDICATE">:predicate:ENUM-OF</item>
			<item const="kTAG_OBJECT" node="term">abdh:Q5.14a</item>
		</EDGE>
	</META>
	<!-- abdh:Q5.14a:3 -->
	<META>
		<TERM ns="abdh:Q5.14a" lid="3">
			<item const="kTAG_LABEL">
				<item>
					<item const="kTAG_LANGUAGE">en</item>
					<item const="kTAG_TEXT"><![CDATA[Both]]></item>
				</item>
			</item>
		</TERM>
		<NODE>
			<item const="kTAG_NODE_TYPE">
				<item>:type:node:enumeration</item>
			</item>
		</NODE>
		<EDGE>
			<item const="kTAG_PREDICATE">:predicate:ENUM-OF</item>
			<item const="kTAG_OBJECT" node="term">abdh:Q5.14a</item>
		</EDGE>
	</META>
	<!-- abdh:Q5.14a:4 -->
	<META>
		<TERM ns="abdh:Q5.14a" lid="4">
			<item const="kTAG_LABEL">
				<item>
					<item const="kTAG_LANGUAGE">en</item>
					<item const="kTAG_TEXT"><![CDATA[Children]]></item>
				</item>
			</item>
		</TERM>
		<NODE>
			<item const="kTAG_NODE_TYPE">
				<item>:type:node:enumeration</item>
			</item>
		</NODE>
		<EDGE>
			<item const="kTAG_PREDICATE">:predicate:ENUM-OF</item>
			<item const="kTAG_OBJECT" node="term">abdh:Q5.14a</item>
		</EDGE>
	</META>
	<!-- abdh:Q5.14a:5 -->
	<META>
		<TERM ns="abdh:Q5.14a" lid="5">
			<item const="kTAG_LABEL">
				<item>
					<item const="kTAG_LANGUAGE">en</item>
					<item const="kTAG_TEXT"><![CDATA[Other]]></item>
				</item>
			</item>
		</TERM>
		<NODE>
			<item const="kTAG_NODE_TYPE">
				<item>:type:node:enumeration</item>
			</item>
		</NODE>
		<EDGE>
			<item const="kTAG_PREDICATE">:predicate:ENUM-OF</item>
			<item const="kTAG_OBJECT" node="term">abdh:Q5.14a</item>
		</EDGE>
	</META>
	
	<!-- abdh:Q5.14b -->
	<META>
		<TERM ns="abdh" lid="Q5.14b">
			<item const="kTAG_LABEL">
				<item>
					<item const="kTAG_LANGUAGE">en</item>
					<item const="kTAG_TEXT"><![CDATA[Who takes care of the species (other specification)]]></item>
				</item>
			</item>
		</TERM>
		<TAG>
			<item const="kTAG_TERMS">
				<item>abdh:Q5.14b</item>
			</item>
			<item const="kTAG_DATA_TYPE">:type:string</item>
			<item const="kTAG_DATA_KIND">
				<item>:type:discrete</item>
				<item>:type:list</item>
				<item>:type:full-text-03</item>
			</item>
			<item const="kTAG_SYNONYM">
				<item>Q5.14b</item>
			</item>
		</TAG>
		<NODE tag="abdh:Q5.14b">
			<item const="kTAG_NODE_TYPE">
				<item>:kind:property-node</item>
			</item>
		</NODE>
		<EDGE>
			<item const="kTAG_PREDICATE">:predicate:PROPERTY-OF</item>
			<item const="kTAG_OBJECT" node="tag">abdh:species</item>
		</EDGE>
	</META>
	
	<!-- abdh:Q5.15a -->
	<META>
		<TERM ns="abdh" lid="Q5.15a">
			<item const="kTAG_LABEL">
				<item>
					<item const="kTAG_LANGUAGE">en</item>
					<item const="kTAG_TEXT"><![CDATA[Who makes the decisions about the management of the species]]></item>
				</item>
			</item>
		</TERM>
		<TAG>
			<item const="kTAG_TERMS">
				<item>abdh:Q5.15a</item>
			</item>
			<item const="kTAG_DATA_TYPE">:type:enum-set</item>
			<item const="kTAG_DATA_KIND">
				<item>:type:categorical</item>
				<item>:type:full-text-03</item>
				<item>:type:summary</item>
			</item>
			<item const="kTAG_SYNONYM">
				<item>Q5.15a</item>
			</item>
		</TAG>
		<NODE tag="abdh:Q5.15a">
			<item const="kTAG_NODE_TYPE">
				<item>:kind:property-node</item>
			</item>
		</NODE>
		<NODE term="abdh:Q5.15a">
			<item const="kTAG_NODE_TYPE">
				<item>:type:node:type</item>
				<item>:kind:enumerated-node</item>
			</item>
		</NODE>
		<EDGE>
			<item const="kTAG_SUBJECT" node="term">abdh:Q5.15a</item>
			<item const="kTAG_PREDICATE">:predicate:TYPE-OF</item>
			<item const="kTAG_OBJECT" node="tag">abdh:Q5.15a</item>
		</EDGE>
		<EDGE>
			<item const="kTAG_SUBJECT" node="tag">abdh:Q5.15a</item>
			<item const="kTAG_PREDICATE">:predicate:PROPERTY-OF</item>
			<item const="kTAG_OBJECT" node="tag">abdh:species</item>
		</EDGE>
	</META>
	<!-- abdh:Q5.15a:1 -->
	<META>
		<TERM ns="abdh:Q5.15a" lid="1">
			<item const="kTAG_LABEL">
				<item>
					<item const="kTAG_LANGUAGE">en</item>
					<item const="kTAG_TEXT"><![CDATA[Husband]]></item>
				</item>
			</item>
		</TERM>
		<NODE>
			<item const="kTAG_NODE_TYPE">
				<item>:type:node:enumeration</item>
			</item>
		</NODE>
		<EDGE>
			<item const="kTAG_PREDICATE">:predicate:ENUM-OF</item>
			<item const="kTAG_OBJECT" node="term">abdh:Q5.15a</item>
		</EDGE>
	</META>
	<!-- abdh:Q5.15a:2 -->
	<META>
		<TERM ns="abdh:Q5.15a" lid="2">
			<item const="kTAG_LABEL">
				<item>
					<item const="kTAG_LANGUAGE">en</item>
					<item const="kTAG_TEXT"><![CDATA[Wife]]></item>
				</item>
			</item>
		</TERM>
		<NODE>
			<item const="kTAG_NODE_TYPE">
				<item>:type:node:enumeration</item>
			</item>
		</NODE>
		<EDGE>
			<item const="kTAG_PREDICATE">:predicate:ENUM-OF</item>
			<item const="kTAG_OBJECT" node="term">abdh:Q5.15a</item>
		</EDGE>
	</META>
	<!-- abdh:Q5.15a:3 -->
	<META>
		<TERM ns="abdh:Q5.15a" lid="3">
			<item const="kTAG_LABEL">
				<item>
					<item const="kTAG_LANGUAGE">en</item>
					<item const="kTAG_TEXT"><![CDATA[Both]]></item>
				</item>
			</item>
		</TERM>
		<NODE>
			<item const="kTAG_NODE_TYPE">
				<item>:type:node:enumeration</item>
			</item>
		</NODE>
		<EDGE>
			<item const="kTAG_PREDICATE">:predicate:ENUM-OF</item>
			<item const="kTAG_OBJECT" node="term">abdh:Q5.15a</item>
		</EDGE>
	</META>
	<!-- abdh:Q5.15a:4 -->
	<META>
		<TERM ns="abdh:Q5.15a" lid="4">
			<item const="kTAG_LABEL">
				<item>
					<item const="kTAG_LANGUAGE">en</item>
					<item const="kTAG_TEXT"><![CDATA[Children]]></item>
				</item>
			</item>
		</TERM>
		<NODE>
			<item const="kTAG_NODE_TYPE">
				<item>:type:node:enumeration</item>
			</item>
		</NODE>
		<EDGE>
			<item const="kTAG_PREDICATE">:predicate:ENUM-OF</item>
			<item const="kTAG_OBJECT" node="term">abdh:Q5.15a</item>
		</EDGE>
	</META>
	<!-- abdh:Q5.15a:5 -->
	<META>
		<TERM ns="abdh:Q5.15a" lid="5">
			<item const="kTAG_LABEL">
				<item>
					<item const="kTAG_LANGUAGE">en</item>
					<item const="kTAG_TEXT"><![CDATA[Other]]></item>
				</item>
			</item>
		</TERM>
		<NODE>
			<item const="kTAG_NODE_TYPE">
				<item>:type:node:enumeration</item>
			</item>
		</NODE>
		<EDGE>
			<item const="kTAG_PREDICATE">:predicate:ENUM-OF</item>
			<item const="kTAG_OBJECT" node="term">abdh:Q5.15a</item>
		</EDGE>
	</META>
	
	<!-- abdh:Q5.15b -->
	<META>
		<TERM ns="abdh" lid="Q5.15b">
			<item const="kTAG_LABEL">
				<item>
					<item const="kTAG_LANGUAGE">en</item>
					<item const="kTAG_TEXT"><![CDATA[Who makes the decisions about the management of the species (other specification)]]></item>
				</item>
			</item>
		</TERM>
		<TAG>
			<item const="kTAG_TERMS">
				<item>abdh:Q5.15b</item>
			</item>
			<item const="kTAG_DATA_TYPE">:type:string</item>
			<item const="kTAG_DATA_KIND">
				<item>:type:discrete</item>
				<item>:type:list</item>
				<item>:type:full-text-03</item>
			</item>
			<item const="kTAG_SYNONYM">
				<item>Q5.15b</item>
			</item>
		</TAG>
		<NODE tag="abdh:Q5.15b">
			<item const="kTAG_NODE_TYPE">
				<item>:kind:property-node</item>
			</item>
		</NODE>
		<EDGE>
			<item const="kTAG_PREDICATE">:predicate:PROPERTY-OF</item>
			<item const="kTAG_OBJECT" node="tag">abdh:species</item>
		</EDGE>
	</META>
	
	<!-- abdh:Q5.16a -->
	<META>
		<TERM ns="abdh" lid="Q5.16a">
			<item const="kTAG_LABEL">
				<item>
					<item const="kTAG_LANGUAGE">en</item>
					<item const="kTAG_TEXT"><![CDATA[Who makes the decisions about the harvesting of the species]]></item>
				</item>
			</item>
		</TERM>
		<TAG>
			<item const="kTAG_TERMS">
				<item>abdh:Q5.16a</item>
			</item>
			<item const="kTAG_DATA_TYPE">:type:enum-set</item>
			<item const="kTAG_DATA_KIND">
				<item>:type:categorical</item>
				<item>:type:full-text-03</item>
				<item>:type:summary</item>
			</item>
			<item const="kTAG_SYNONYM">
				<item>Q5.16a</item>
			</item>
		</TAG>
		<NODE tag="abdh:Q5.16a">
			<item const="kTAG_NODE_TYPE">
				<item>:kind:property-node</item>
			</item>
		</NODE>
		<NODE term="abdh:Q5.16a">
			<item const="kTAG_NODE_TYPE">
				<item>:type:node:type</item>
				<item>:kind:enumerated-node</item>
			</item>
		</NODE>
		<EDGE>
			<item const="kTAG_SUBJECT" node="term">abdh:Q5.16a</item>
			<item const="kTAG_PREDICATE">:predicate:TYPE-OF</item>
			<item const="kTAG_OBJECT" node="tag">abdh:Q5.16a</item>
		</EDGE>
		<EDGE>
			<item const="kTAG_SUBJECT" node="tag">abdh:Q5.16a</item>
			<item const="kTAG_PREDICATE">:predicate:PROPERTY-OF</item>
			<item const="kTAG_OBJECT" node="tag">abdh:species</item>
		</EDGE>
	</META>
	<!-- abdh:Q5.16a:1 -->
	<META>
		<TERM ns="abdh:Q5.16a" lid="1">
			<item const="kTAG_LABEL">
				<item>
					<item const="kTAG_LANGUAGE">en</item>
					<item const="kTAG_TEXT"><![CDATA[Husband]]></item>
				</item>
			</item>
		</TERM>
		<NODE>
			<item const="kTAG_NODE_TYPE">
				<item>:type:node:enumeration</item>
			</item>
		</NODE>
		<EDGE>
			<item const="kTAG_PREDICATE">:predicate:ENUM-OF</item>
			<item const="kTAG_OBJECT" node="term">abdh:Q5.16a</item>
		</EDGE>
	</META>
	<!-- abdh:Q5.16a:2 -->
	<META>
		<TERM ns="abdh:Q5.16a" lid="2">
			<item const="kTAG_LABEL">
				<item>
					<item const="kTAG_LANGUAGE">en</item>
					<item const="kTAG_TEXT"><![CDATA[Wife]]></item>
				</item>
			</item>
		</TERM>
		<NODE>
			<item const="kTAG_NODE_TYPE">
				<item>:type:node:enumeration</item>
			</item>
		</NODE>
		<EDGE>
			<item const="kTAG_PREDICATE">:predicate:ENUM-OF</item>
			<item const="kTAG_OBJECT" node="term">abdh:Q5.16a</item>
		</EDGE>
	</META>
	<!-- abdh:Q5.16a:3 -->
	<META>
		<TERM ns="abdh:Q5.16a" lid="3">
			<item const="kTAG_LABEL">
				<item>
					<item const="kTAG_LANGUAGE">en</item>
					<item const="kTAG_TEXT"><![CDATA[Both]]></item>
				</item>
			</item>
		</TERM>
		<NODE>
			<item const="kTAG_NODE_TYPE">
				<item>:type:node:enumeration</item>
			</item>
		</NODE>
		<EDGE>
			<item const="kTAG_PREDICATE">:predicate:ENUM-OF</item>
			<item const="kTAG_OBJECT" node="term">abdh:Q5.16a</item>
		</EDGE>
	</META>
	<!-- abdh:Q5.16a:4 -->
	<META>
		<TERM ns="abdh:Q5.16a" lid="4">
			<item const="kTAG_LABEL">
				<item>
					<item const="kTAG_LANGUAGE">en</item>
					<item const="kTAG_TEXT"><![CDATA[Children]]></item>
				</item>
			</item>
		</TERM>
		<NODE>
			<item const="kTAG_NODE_TYPE">
				<item>:type:node:enumeration</item>
			</item>
		</NODE>
		<EDGE>
			<item const="kTAG_PREDICATE">:predicate:ENUM-OF</item>
			<item const="kTAG_OBJECT" node="term">abdh:Q5.16a</item>
		</EDGE>
	</META>
	<!-- abdh:Q5.16a:5 -->
	<META>
		<TERM ns="abdh:Q5.16a" lid="5">
			<item const="kTAG_LABEL">
				<item>
					<item const="kTAG_LANGUAGE">en</item>
					<item const="kTAG_TEXT"><![CDATA[Other]]></item>
				</item>
			</item>
		</TERM>
		<NODE>
			<item const="kTAG_NODE_TYPE">
				<item>:type:node:enumeration</item>
			</item>
		</NODE>
		<EDGE>
			<item const="kTAG_PREDICATE">:predicate:ENUM-OF</item>
			<item const="kTAG_OBJECT" node="term">abdh:Q5.16a</item>
		</EDGE>
	</META>
	
	<!-- abdh:Q5.16b -->
	<META>
		<TERM ns="abdh" lid="Q5.16b">
			<item const="kTAG_LABEL">
				<item>
					<item const="kTAG_LANGUAGE">en</item>
					<item const="kTAG_TEXT"><![CDATA[Who makes the decisions about the harvesting of the species (other specification)]]></item>
				</item>
			</item>
		</TERM>
		<TAG>
			<item const="kTAG_TERMS">
				<item>abdh:Q5.16b</item>
			</item>
			<item const="kTAG_DATA_TYPE">:type:string</item>
			<item const="kTAG_DATA_KIND">
				<item>:type:discrete</item>
				<item>:type:list</item>
				<item>:type:full-text-03</item>
			</item>
			<item const="kTAG_SYNONYM">
				<item>Q5.16b</item>
			</item>
		</TAG>
		<NODE tag="abdh:Q5.16b">
			<item const="kTAG_NODE_TYPE">
				<item>:kind:property-node</item>
			</item>
		</NODE>
		<EDGE>
			<item const="kTAG_PREDICATE">:predicate:PROPERTY-OF</item>
			<item const="kTAG_OBJECT" node="tag">abdh:species</item>
		</EDGE>
	</META>
	
	<!-- abdh:Q5.17a -->
	<META>
		<TERM ns="abdh" lid="Q5.17a">
			<item const="kTAG_LABEL">
				<item>
					<item const="kTAG_LANGUAGE">en</item>
					<item const="kTAG_TEXT"><![CDATA[Who makes the decisions about the uses of the species]]></item>
				</item>
			</item>
		</TERM>
		<TAG>
			<item const="kTAG_TERMS">
				<item>abdh:Q5.17a</item>
			</item>
			<item const="kTAG_DATA_TYPE">:type:enum-set</item>
			<item const="kTAG_DATA_KIND">
				<item>:type:categorical</item>
				<item>:type:full-text-03</item>
				<item>:type:summary</item>
			</item>
			<item const="kTAG_SYNONYM">
				<item>Q5.17a</item>
			</item>
		</TAG>
		<NODE tag="abdh:Q5.17a">
			<item const="kTAG_NODE_TYPE">
				<item>:kind:property-node</item>
			</item>
		</NODE>
		<NODE term="abdh:Q5.17a">
			<item const="kTAG_NODE_TYPE">
				<item>:type:node:type</item>
				<item>:kind:enumerated-node</item>
			</item>
		</NODE>
		<EDGE>
			<item const="kTAG_SUBJECT" node="term">abdh:Q5.17a</item>
			<item const="kTAG_PREDICATE">:predicate:TYPE-OF</item>
			<item const="kTAG_OBJECT" node="tag">abdh:Q5.17a</item>
		</EDGE>
		<EDGE>
			<item const="kTAG_SUBJECT" node="tag">abdh:Q5.17a</item>
			<item const="kTAG_PREDICATE">:predicate:PROPERTY-OF</item>
			<item const="kTAG_OBJECT" node="tag">abdh:species</item>
		</EDGE>
	</META>
	<!-- abdh:Q5.17a:1 -->
	<META>
		<TERM ns="abdh:Q5.17a" lid="1">
			<item const="kTAG_LABEL">
				<item>
					<item const="kTAG_LANGUAGE">en</item>
					<item const="kTAG_TEXT"><![CDATA[Husband]]></item>
				</item>
			</item>
		</TERM>
		<NODE>
			<item const="kTAG_NODE_TYPE">
				<item>:type:node:enumeration</item>
			</item>
		</NODE>
		<EDGE>
			<item const="kTAG_PREDICATE">:predicate:ENUM-OF</item>
			<item const="kTAG_OBJECT" node="term">abdh:Q5.17a</item>
		</EDGE>
	</META>
	<!-- abdh:Q5.17a:2 -->
	<META>
		<TERM ns="abdh:Q5.17a" lid="2">
			<item const="kTAG_LABEL">
				<item>
					<item const="kTAG_LANGUAGE">en</item>
					<item const="kTAG_TEXT"><![CDATA[Wife]]></item>
				</item>
			</item>
		</TERM>
		<NODE>
			<item const="kTAG_NODE_TYPE">
				<item>:type:node:enumeration</item>
			</item>
		</NODE>
		<EDGE>
			<item const="kTAG_PREDICATE">:predicate:ENUM-OF</item>
			<item const="kTAG_OBJECT" node="term">abdh:Q5.17a</item>
		</EDGE>
	</META>
	<!-- abdh:Q5.17a:3 -->
	<META>
		<TERM ns="abdh:Q5.17a" lid="3">
			<item const="kTAG_LABEL">
				<item>
					<item const="kTAG_LANGUAGE">en</item>
					<item const="kTAG_TEXT"><![CDATA[Both]]></item>
				</item>
			</item>
		</TERM>
		<NODE>
			<item const="kTAG_NODE_TYPE">
				<item>:type:node:enumeration</item>
			</item>
		</NODE>
		<EDGE>
			<item const="kTAG_PREDICATE">:predicate:ENUM-OF</item>
			<item const="kTAG_OBJECT" node="term">abdh:Q5.17a</item>
		</EDGE>
	</META>
	<!-- abdh:Q5.17a:4 -->
	<META>
		<TERM ns="abdh:Q5.17a" lid="4">
			<item const="kTAG_LABEL">
				<item>
					<item const="kTAG_LANGUAGE">en</item>
					<item const="kTAG_TEXT"><![CDATA[Children]]></item>
				</item>
			</item>
		</TERM>
		<NODE>
			<item const="kTAG_NODE_TYPE">
				<item>:type:node:enumeration</item>
			</item>
		</NODE>
		<EDGE>
			<item const="kTAG_PREDICATE">:predicate:ENUM-OF</item>
			<item const="kTAG_OBJECT" node="term">abdh:Q5.17a</item>
		</EDGE>
	</META>
	<!-- abdh:Q5.17a:5 -->
	<META>
		<TERM ns="abdh:Q5.17a" lid="5">
			<item const="kTAG_LABEL">
				<item>
					<item const="kTAG_LANGUAGE">en</item>
					<item const="kTAG_TEXT"><![CDATA[Other]]></item>
				</item>
			</item>
		</TERM>
		<NODE>
			<item const="kTAG_NODE_TYPE">
				<item>:type:node:enumeration</item>
			</item>
		</NODE>
		<EDGE>
			<item const="kTAG_PREDICATE">:predicate:ENUM-OF</item>
			<item const="kTAG_OBJECT" node="term">abdh:Q5.17a</item>
		</EDGE>
	</META>
	
	<!-- abdh:Q5.17b -->
	<META>
		<TERM ns="abdh" lid="Q5.17b">
			<item const="kTAG_LABEL">
				<item>
					<item const="kTAG_LANGUAGE">en</item>
					<item const="kTAG_TEXT"><![CDATA[Who makes the decisions about the uses of the species (other specification)]]></item>
				</item>
			</item>
		</TERM>
		<TAG>
			<item const="kTAG_TERMS">
				<item>abdh:Q5.17b</item>
			</item>
			<item const="kTAG_DATA_TYPE">:type:string</item>
			<item const="kTAG_DATA_KIND">
				<item>:type:discrete</item>
				<item>:type:list</item>
				<item>:type:full-text-03</item>
			</item>
			<item const="kTAG_SYNONYM">
				<item>Q5.17b</item>
			</item>
		</TAG>
		<NODE tag="abdh:Q5.17b">
			<item const="kTAG_NODE_TYPE">
				<item>:kind:property-node</item>
			</item>
		</NODE>
		<EDGE>
			<item const="kTAG_PREDICATE">:predicate:PROPERTY-OF</item>
			<item const="kTAG_OBJECT" node="tag">abdh:species</item>
		</EDGE>
	</META>
	
	<!-- abdh:Q5.18a -->
	<META>
		<TERM ns="abdh" lid="Q5.18a">
			<item const="kTAG_LABEL">
				<item>
					<item const="kTAG_LANGUAGE">en</item>
					<item const="kTAG_TEXT"><![CDATA[Who makes the decisions about the sale for various products from the species]]></item>
				</item>
			</item>
		</TERM>
		<TAG>
			<item const="kTAG_TERMS">
				<item>abdh:Q5.18a</item>
			</item>
			<item const="kTAG_DATA_TYPE">:type:enum-set</item>
			<item const="kTAG_DATA_KIND">
				<item>:type:categorical</item>
				<item>:type:full-text-03</item>
				<item>:type:summary</item>
			</item>
			<item const="kTAG_SYNONYM">
				<item>Q5.18a</item>
			</item>
		</TAG>
		<NODE tag="abdh:Q5.18a">
			<item const="kTAG_NODE_TYPE">
				<item>:kind:property-node</item>
			</item>
		</NODE>
		<NODE term="abdh:Q5.18a">
			<item const="kTAG_NODE_TYPE">
				<item>:type:node:type</item>
				<item>:kind:enumerated-node</item>
			</item>
		</NODE>
		<EDGE>
			<item const="kTAG_SUBJECT" node="term">abdh:Q5.18a</item>
			<item const="kTAG_PREDICATE">:predicate:TYPE-OF</item>
			<item const="kTAG_OBJECT" node="tag">abdh:Q5.18a</item>
		</EDGE>
		<EDGE>
			<item const="kTAG_SUBJECT" node="tag">abdh:Q5.18a</item>
			<item const="kTAG_PREDICATE">:predicate:PROPERTY-OF</item>
			<item const="kTAG_OBJECT" node="tag">abdh:species</item>
		</EDGE>
	</META>
	<!-- abdh:Q5.18a:1 -->
	<META>
		<TERM ns="abdh:Q5.18a" lid="1">
			<item const="kTAG_LABEL">
				<item>
					<item const="kTAG_LANGUAGE">en</item>
					<item const="kTAG_TEXT"><![CDATA[Husband]]></item>
				</item>
			</item>
		</TERM>
		<NODE>
			<item const="kTAG_NODE_TYPE">
				<item>:type:node:enumeration</item>
			</item>
		</NODE>
		<EDGE>
			<item const="kTAG_PREDICATE">:predicate:ENUM-OF</item>
			<item const="kTAG_OBJECT" node="term">abdh:Q5.18a</item>
		</EDGE>
	</META>
	<!-- abdh:Q5.18a:2 -->
	<META>
		<TERM ns="abdh:Q5.18a" lid="2">
			<item const="kTAG_LABEL">
				<item>
					<item const="kTAG_LANGUAGE">en</item>
					<item const="kTAG_TEXT"><![CDATA[Wife]]></item>
				</item>
			</item>
		</TERM>
		<NODE>
			<item const="kTAG_NODE_TYPE">
				<item>:type:node:enumeration</item>
			</item>
		</NODE>
		<EDGE>
			<item const="kTAG_PREDICATE">:predicate:ENUM-OF</item>
			<item const="kTAG_OBJECT" node="term">abdh:Q5.18a</item>
		</EDGE>
	</META>
	<!-- abdh:Q5.18a:3 -->
	<META>
		<TERM ns="abdh:Q5.18a" lid="3">
			<item const="kTAG_LABEL">
				<item>
					<item const="kTAG_LANGUAGE">en</item>
					<item const="kTAG_TEXT"><![CDATA[Both]]></item>
				</item>
			</item>
		</TERM>
		<NODE>
			<item const="kTAG_NODE_TYPE">
				<item>:type:node:enumeration</item>
			</item>
		</NODE>
		<EDGE>
			<item const="kTAG_PREDICATE">:predicate:ENUM-OF</item>
			<item const="kTAG_OBJECT" node="term">abdh:Q5.18a</item>
		</EDGE>
	</META>
	<!-- abdh:Q5.18a:4 -->
	<META>
		<TERM ns="abdh:Q5.18a" lid="4">
			<item const="kTAG_LABEL">
				<item>
					<item const="kTAG_LANGUAGE">en</item>
					<item const="kTAG_TEXT"><![CDATA[Children]]></item>
				</item>
			</item>
		</TERM>
		<NODE>
			<item const="kTAG_NODE_TYPE">
				<item>:type:node:enumeration</item>
			</item>
		</NODE>
		<EDGE>
			<item const="kTAG_PREDICATE">:predicate:ENUM-OF</item>
			<item const="kTAG_OBJECT" node="term">abdh:Q5.18a</item>
		</EDGE>
	</META>
	<!-- abdh:Q5.18a:5 -->
	<META>
		<TERM ns="abdh:Q5.18a" lid="5">
			<item const="kTAG_LABEL">
				<item>
					<item const="kTAG_LANGUAGE">en</item>
					<item const="kTAG_TEXT"><![CDATA[Other]]></item>
				</item>
			</item>
		</TERM>
		<NODE>
			<item const="kTAG_NODE_TYPE">
				<item>:type:node:enumeration</item>
			</item>
		</NODE>
		<EDGE>
			<item const="kTAG_PREDICATE">:predicate:ENUM-OF</item>
			<item const="kTAG_OBJECT" node="term">abdh:Q5.18a</item>
		</EDGE>
	</META>
	
	<!-- abdh:Q5.18b -->
	<META>
		<TERM ns="abdh" lid="Q5.18b">
			<item const="kTAG_LABEL">
				<item>
					<item const="kTAG_LANGUAGE">en</item>
					<item const="kTAG_TEXT"><![CDATA[Who makes the decisions about sale for various products from the species (other specification)]]></item>
				</item>
			</item>
		</TERM>
		<TAG>
			<item const="kTAG_TERMS">
				<item>abdh:Q5.18b</item>
			</item>
			<item const="kTAG_DATA_TYPE">:type:string</item>
			<item const="kTAG_DATA_KIND">
				<item>:type:discrete</item>
				<item>:type:list</item>
				<item>:type:full-text-03</item>
			</item>
			<item const="kTAG_SYNONYM">
				<item>Q5.18b</item>
			</item>
		</TAG>
		<NODE tag="abdh:Q5.18b">
			<item const="kTAG_NODE_TYPE">
				<item>:kind:property-node</item>
			</item>
		</NODE>
		<EDGE>
			<item const="kTAG_PREDICATE">:predicate:PROPERTY-OF</item>
			<item const="kTAG_OBJECT" node="tag">abdh:species</item>
		</EDGE>
	</META>
</METADATA>
